README.md
setup.py
demo/ychy_downloader.py
spider_search.egg-info/PKG-INFO
spider_search.egg-info/SOURCES.txt
spider_search.egg-info/dependency_links.txt
spider_search.egg-info/requires.txt
spider_search.egg-info/top_level.txt
spidersearch/__init__.py
spidersearch/spidersearch.py
spidersearch/common/__init__.py
spidersearch/common/log.py
spidersearch/element/__init__.py
spidersearch/element/element.py
spidersearch/handler/__init__.py
spidersearch/handler/resource.py