Metadata-Version: 1.2
Name: spider-search
Version: 0.0.2
Summary: Search resource from web page
Home-page: https://gitee.com/dengshaolin/spider-search
License: UNKNOWN
Platform: UNKNOWN
Requires-Python: >=3.6
